{
  "alumns": [
    {
      "id": "43adaw212",
      "name": "Ismael Bola",
      "img": "https://firebasestorage.googleapis.com/v0/b/testfb-login.appspot.com/o/upload%2F43adaw212.jpg?alt=media&token=ea493f0b-cc91-4dcd-91b6-774efafdf667",
      "courses": [
        {
          "name": "Angular EOI",
          "img": "https://picsum.photos/id/640/536/354.jpg",
          "hours": 320,
          "description": "",
          "skills": [],
          "professors": [],
          "area": "",
          "year": "",
          "modality": ""
        }
      ],
      "birthday": "12/08/1999",
      "laborSituation": "Desempleado",
      "phone": "365354632",
      "city": "Las Palmas",
      "contactEmail": "ismaelbg_99@hotmail.com",
      "experiences": [
        {
          "company": "TAC7",
          "time": "64"
        },
        {
          "company": "TAC24",
          "time": "89"
        },
        {
          "company": "TAC nº3",
          "time": "700"
        },
        {
          "company": "TAC nº3",
          "time": "700"
        }
      ],
      "password": "12345",
      "loginEmail": "ismaelbg_99@hotmail.com",
      "mainCourse": "Angular EOI",
      "description": "NADA",
      "decription": "NADA"
    },
    {
      "id": "43adaw213",
      "name": "Manu Moya Yanes",
      "img": "https://randomuser.me/api/portraits/men/15.jpg",
      "courses": [
        {
          "name": "Angular EOI",
          "img": "https://picsum.photos/id/640/536/354.jpg",
          "hours": 320,
          "description": "",
          "skills": [],
          "professors": [],
          "area": "",
          "year": "",
          "modality": ""
        }
      ],
      "birthday": "12/08/1991",
      "laborSituation": "",
      "phone": "235243486",
      "city": "Las Palmas",
      "contactEmail": "manu@hotmail.com",
      "experiences": [],
      "password": "1234567",
      "loginEmail": "manu@hotmail.com",
      "mainCourse": "Angular EOI",
      "description": "awdwad"
    },
    {
      "id": "43adaw214",
      "name": "Ana Valdemoro Ramírez",
      "img": "https://randomuser.me/api/portraits/women/15.jpg",
      "courses": [
        {
          "name": "Angular EOI",
          "img": "https://picsum.photos/id/640/536/354.jpg",
          "hours": 320,
          "description": "",
          "skills": [],
          "professors": [],
          "area": "",
          "year": "",
          "modality": ""
        }
      ],
      "birthday": "4/09/1998",
      "laborSituation": "Desempleado",
      "phone": "23573235",
      "city": "Las Palmas",
      "contactEmail": "ana_v_r@hotmail.com",
      "experiences": [],
      "password": "12345",
      "loginEmail": "Anita.valde@hotmail.com",
      "mainCourse": "Angular EOI"
    },
    {
      "id": "43adaw215",
      "name": "Aisha Yanez",
      "img": "https://randomuser.me/api/portraits/women/14.jpg",
      "courses": [
        {
          "name": "Angular EOI",
          "img": "https://picsum.photos/id/640/536/354.jpg",
          "hours": 320,
          "description": "",
          "skills": [],
          "professors": [],
          "area": "",
          "year": "",
          "modality": ""
        },
        {
          "name": "IONIC EOI",
          "img": "https://picsum.photos/id/640/536/354.jpg",
          "hours": 320,
          "description": "",
          "skills": [],
          "professors": [],
          "area": "",
          "year": "",
          "modality": ""
        }
      ],
      "birthday": "17/01/1998",
      "laborSituation": "Estudiante",
      "phone": "23573457",
      "city": "Las Palmas",
      "contactEmail": "Aisha.ynz@hotmail.com",
      "experiences": [],
      "password": "12345",
      "loginEmail": "Anita.ynz@hotmail.com",
      "mainCourse": "Angular EOI"
    },
    {
      "name": "Daniel Sosa",
      "id": "_9914a19eo",
      "password": "12345",
      "loginEmail": "dani@gmail.com",
      "mainCourse": "Marketing Digital",
      "courses": [
        {
          "name": "Marketing Digital",
          "hours": 300,
          "img": "https://d3t4nwcgmfrp9x.cloudfront.net/upload/cinco-errores-comunes-las-empresas-espanolas-marketing-digital.jpg",
          "description": "Conceptos Básicos de Marketing aplicados a la era Digital",
          "skills": [
            "Diseño",
            "Redes Sociales"
          ],
          "professors": [
            "Lola Flores",
            "Elisabet Cañas"
          ],
          "area": "Marketing y diseño",
          "year": "2020",
          "modality": "presencial"
        }
      ]
    },
    {
      "name": "Lola perez",
      "loginEmail": "lolalita@gmail.com",
      "password": 12345,
      "mainCourse": "Marketing Digital",
      "courses": [
        {
          "name": "Marketing Digital",
          "hours": 300,
          "img": "https://d3t4nwcgmfrp9x.cloudfront.net/upload/cinco-errores-comunes-las-empresas-espanolas-marketing-digital.jpg",
          "description": "Conceptos Básicos de Marketing aplicados a la era Digital",
          "skills": [
            "Diseño",
            "Redes Sociales"
          ],
          "professors": [
            "Lola Flores",
            "Elisabet Cañas"
          ],
          "area": "Marketing y diseño",
          "year": "2020",
          "modality": "presencial"
        }
      ],
      "id": "qAjMxjN"
    },
    {
      "name": "pepa mijaaa",
      "loginEmail": "pepa@gmail.com",
      "password": 12345,
      "mainCourse": "Desarrollo Web Angular",
      "courses": [
        {
          "name": "Desarrollo Web Angular",
          "hours": 250,
          "description": "Aprendizaje profundo de Angular",
          "skills": [
            "html",
            "Css",
            "Angular",
            "TypeScript"
          ],
          "professors": [
            "Jose Luis",
            "Alcibiades",
            "Alejandro de Juan",
            "Fernando Martín"
          ],
          "area": "Desarrollo Web",
          "year": "2020",
          "modality": "online"
        }
      ],
      "id": "AuLEkhX"
    }
  ],
  "administrators": [
    {
      "email": "admin",
      "password": "1234"
    }
  ]
}